funnydspy/__init__.py
funnydspy-0.4.0.dist-info/licenses/LICENSE
funnydspy-0.4.0.dist-info/METADATA
funnydspy-0.4.0.dist-info/WHEEL
funnydspy-0.4.0.dist-info/top_level.txt
funnydspy-0.4.0.dist-info/RECORD
