Metadata-Version: 2.4
Name: funnydspy
Version: 0.4.0
Summary: Vanilla-Python ergonomics on top of DSPy
Author: FunnyDSPy Contributors
License: MIT
Project-URL: Homepage, https://github.com/MaximeRivest/funnydspy
Project-URL: Repository, https://github.com/MaximeRivest/funnydspy
Project-URL: Issues, https://github.com/MaximeRivest/funnydspy/issues
Project-URL: Documentation, https://github.com/MaximeRivest/funnydspy#readme
Keywords: dspy,llm,language-models,ai,machine-learning,nlp
Classifier: Development Status :: 3 - Alpha
Classifier: Intended Audience :: Developers
Classifier: Operating System :: OS Independent
Classifier: Programming Language :: Python :: 3
Classifier: Programming Language :: Python :: 3.8
Classifier: Programming Language :: Python :: 3.9
Classifier: Programming Language :: Python :: 3.10
Classifier: Programming Language :: Python :: 3.11
Classifier: Programming Language :: Python :: 3.12
Classifier: Topic :: Scientific/Engineering :: Artificial Intelligence
Classifier: Topic :: Software Development :: Libraries :: Python Modules
Requires-Python: >=3.8
License-File: LICENSE
Requires-Dist: dspy-ai>=2.6.0
Requires-Dist: fastcore>=1.8.0
Requires-Dist: typing-extensions>=4.0.0
Provides-Extra: dev
Requires-Dist: pytest>=6.0; extra == "dev"
Requires-Dist: pytest-cov; extra == "dev"
Requires-Dist: black; extra == "dev"
Requires-Dist: isort; extra == "dev"
Requires-Dist: flake8; extra == "dev"
Dynamic: license-file
